discretization/__init__.py
discretization/booleanization.py
discretization/entropy_based_discretization.py
discretization/information_theory.py
rsclassifier/__init__.py
rsclassifier/feature_selection.py
rsclassifier/quine_mccluskey.py
rsclassifier/rule_set_classifier.py
rsclassifier-1.5.3.dist-info/LICENSE
rsclassifier-1.5.3.dist-info/METADATA
rsclassifier-1.5.3.dist-info/WHEEL
rsclassifier-1.5.3.dist-info/top_level.txt
rsclassifier-1.5.3.dist-info/RECORD
