Metadata-Version: 2.1
Name: rsclassifier
Version: 1.5.3
Summary: Package for training rule set classifiers for tabular data.
Author: Reijo Jaakkola
Author-email: Reijo Jaakkola <jaakkolareijo@hotmail.com>
License: MIT
Project-URL: homepage, https://github.com/ReijoJaakkola/rsclassifier
Classifier: Programming Language :: Python :: 3
Classifier: License :: OSI Approved :: MIT License
Classifier: Operating System :: OS Independent
Requires-Python: >=3.6
License-File: LICENSE
Requires-Dist: numpy
Requires-Dist: pandas
Requires-Dist: scikit-learn
Requires-Dist: scipy
Requires-Dist: tqdm
